CHANGES.rst
LICENSE.rst
MANIFEST.in
README.rst
setup.cfg
setup.py
docs/conf.py
docs/index.rst
src/kcrw/__init__.py
src/kcrw.tinymce_imagedrop.egg-info/PKG-INFO
src/kcrw.tinymce_imagedrop.egg-info/SOURCES.txt
src/kcrw.tinymce_imagedrop.egg-info/dependency_links.txt
src/kcrw.tinymce_imagedrop.egg-info/entry_points.txt
src/kcrw.tinymce_imagedrop.egg-info/namespace_packages.txt
src/kcrw.tinymce_imagedrop.egg-info/not-zip-safe
src/kcrw.tinymce_imagedrop.egg-info/requires.txt
src/kcrw.tinymce_imagedrop.egg-info/top_level.txt
src/kcrw/tinymce_imagedrop/__init__.py
src/kcrw/tinymce_imagedrop/configure.zcml
src/kcrw/tinymce_imagedrop/interfaces.py
src/kcrw/tinymce_imagedrop/setuphandlers.py
src/kcrw/tinymce_imagedrop/testing.py
src/kcrw/tinymce_imagedrop/view.py
src/kcrw/tinymce_imagedrop/profiles/default/browserlayer.xml
src/kcrw/tinymce_imagedrop/profiles/default/metadata.xml
src/kcrw/tinymce_imagedrop/profiles/default/registry.xml
src/kcrw/tinymce_imagedrop/profiles/uninstall/browserlayer.xml
src/kcrw/tinymce_imagedrop/profiles/uninstall/registry.xml
src/kcrw/tinymce_imagedrop/static/tinymce_image_paste.js
src/kcrw/tinymce_imagedrop/tests/__init__.py
src/kcrw/tinymce_imagedrop/tests/test_setup.py