Metadata-Version: 1.2
Name: kcrw.tinymce-imagedrop
Version: 1.0.1
Summary: A Plone add-on that adds image drag and drop to TinyMCE 4 in Plone.
Home-page: https://github.com/collective/kcrw.tinymce_imagedrop
Author: Alec Mitchell
Author-email: alecpm@gmail.com
License: GPL version 2
Keywords: Python Plone CMS
Platform: UNKNOWN
Classifier: Environment :: Web Environment
Classifier: Framework :: Plone
Classifier: Framework :: Plone :: Addon
Classifier: Framework :: Plone :: 5.2
Classifier: Framework :: Plone :: 5.1
Classifier: Framework :: Plone :: 4.3
Classifier: Programming Language :: Python
Classifier: Programming Language :: Python :: 2.7
Classifier: Programming Language :: Python :: 3.7
Classifier: Operating System :: OS Independent
Classifier: License :: OSI Approved :: GNU General Public License v2 (GPLv2)
Requires-Python: ==2.7, >=3.6
